.travis.yml
AUTHORS
CHANGES
LICENSE
MANIFEST.in
README
setup.py
lantz/qt/__init__.py
lantz/qt/__main__.py
lantz/qt/app.py
lantz/qt/config.py
lantz/qt/connect.py
lantz/qt/log.py
lantz/qt/objwrapper.py
lantz/qt/assets/fedora.png
lantz/qt/assets/fungen.ui
lantz/qt/assets/scanfrequency.ui
lantz/qt/blocks/__init__.py
lantz/qt/blocks/chart.py
lantz/qt/blocks/feat.py
lantz/qt/blocks/featscan.py
lantz/qt/blocks/layouts.py
lantz/qt/blocks/left_main_center.ui
lantz/qt/blocks/loop.py
lantz/qt/blocks/loop.ui
lantz/qt/blocks/placeholder.ui
lantz/qt/blocks/scan.py
lantz/qt/blocks/scan.ui
lantz/qt/blocks/toolbar_left_right.ui
lantz/qt/blocks/wlayout.py
lantz/qt/utils/__init__.py
lantz/qt/utils/docscrape.py
lantz/qt/utils/qt.py
lantz/qt/utils/qt_loaders.py
lantz/qt/utils/uic.py
lantz/qt/widgets/__init__.py
lantz/qt/widgets/common.py
lantz/qt/widgets/dialog_action.py
lantz/qt/widgets/dialog_units.py
lantz/qt/widgets/feat.py
lantz/qt/widgets/initialize.py
lantz/qt/widgets/nonnumeric.py
lantz/qt/widgets/numeric.py
lantz/qt/widgets/testgui.py
lantz_qt.egg-info/PKG-INFO
lantz_qt.egg-info/SOURCES.txt
lantz_qt.egg-info/dependency_links.txt
lantz_qt.egg-info/entry_points.txt
lantz_qt.egg-info/not-zip-safe
lantz_qt.egg-info/requires.txt
lantz_qt.egg-info/top_level.txt