Metadata-Version: 1.1
Name: lantz-qt
Version: 0.5.3
Summary: Instrumentation framework
Home-page: https://github.com/lantzproject
Author: Hernan E. Grecco
Author-email: hernan.grecco@gmail.com
License: BSD
Keywords: measurement control instrumentation science
Platform: any
Classifier: Development Status :: 4 - Beta
Classifier: Intended Audience :: Developers
Classifier: Intended Audience :: Science/Research
Classifier: License :: OSI Approved :: BSD License
Classifier: Operating System :: MacOS :: MacOS X
Classifier: Operating System :: Microsoft :: Windows
Classifier: Operating System :: POSIX
Classifier: Programming Language :: Python
Classifier: Programming Language :: Python :: 3.6
Classifier: Topic :: Scientific/Engineering
Classifier: Topic :: Software Development :: Libraries
